dbbase/__init__.py
dbbase/_version.py
dbbase/base.py
dbbase/column_types.py
dbbase/doc_utils.py
dbbase/maint.py
dbbase/model.py
dbbase/serializers.py
dbbase/utils.py
dbbase-0.3.10.dist-info/LICENSE.txt
dbbase-0.3.10.dist-info/METADATA
dbbase-0.3.10.dist-info/WHEEL
dbbase-0.3.10.dist-info/top_level.txt
dbbase-0.3.10.dist-info/RECORD
