Metadata-Version: 2.1
Name: dbbase
Version: 0.3.10
Summary: A base implementation of SQLAlchemy models that incorporates the query and session variables within the model objects.
Home-page: https://sidorof.github.io/dbbase/
Author: Donald Smiley
Author-email: dsmiley@sidorof.com
License: MIT
Platform: UNKNOWN
Classifier: Development Status :: 3 - Alpha
Classifier: Intended Audience :: Developers
Classifier: License :: OSI Approved :: MIT License
Classifier: Topic :: Software Development
Classifier: Programming Language :: Python
Classifier: Programming Language :: Python :: 3.6
Classifier: Programming Language :: Python :: 3.7
Classifier: Programming Language :: Python :: 3.8
Classifier: Programming Language :: Python :: 3.9
Requires-Python: >=3.6
Requires-Dist: sqlalchemy
Provides-Extra: dev
Requires-Dist: unittest ; extra == 'dev'
